libgalpy.cp311-win_amd64.pyd
galpy/__init__.py
galpy/actionAngle/__init__.py
galpy/actionAngle/actionAngle.py
galpy/actionAngle/actionAngleAdiabatic.py
galpy/actionAngle/actionAngleAdiabaticGrid.py
galpy/actionAngle/actionAngleAdiabatic_c.py
galpy/actionAngle/actionAngleHarmonic.py
galpy/actionAngle/actionAngleHarmonicInverse.py
galpy/actionAngle/actionAngleInverse.py
galpy/actionAngle/actionAngleIsochrone.py
galpy/actionAngle/actionAngleIsochroneApprox.py
galpy/actionAngle/actionAngleIsochroneInverse.py
galpy/actionAngle/actionAngleSpherical.py
galpy/actionAngle/actionAngleStaeckel.py
galpy/actionAngle/actionAngleStaeckelGrid.py
galpy/actionAngle/actionAngleStaeckel_c.py
galpy/actionAngle/actionAngleTorus.py
galpy/actionAngle/actionAngleTorus_c.py
galpy/actionAngle/actionAngleVertical.py
galpy/actionAngle/actionAngleVerticalInverse.py
galpy/actionAngle/actionAngleTorus_c_ext/galpyPot.h
galpy/actionAngle/actionAngle_c_ext/actionAngle.h
galpy/actionAngle/actionAngle_c_ext/actionAngleAdiabatic.c
galpy/actionAngle/actionAngle_c_ext/actionAngleStaeckel.c
galpy/df/__init__.py
galpy/df/constantbetaHernquistdf.py
galpy/df/constantbetadf.py
galpy/df/df.py
galpy/df/diskdf.py
galpy/df/eddingtondf.py
galpy/df/evolveddiskdf.py
galpy/df/isotropicHernquistdf.py
galpy/df/isotropicNFWdf.py
galpy/df/isotropicPlummerdf.py
galpy/df/jeans.py
galpy/df/kingdf.py
galpy/df/osipkovmerrittHernquistdf.py
galpy/df/osipkovmerrittNFWdf.py
galpy/df/osipkovmerrittdf.py
galpy/df/quasiisothermaldf.py
galpy/df/sphericaldf.py
galpy/df/streamdf.py
galpy/df/streamgapdf.py
galpy/df/streamspraydf.py
galpy/df/surfaceSigmaProfile.py
galpy/df/data/dfcorrection_dehnendf_expSurfaceSigmaProfile_0.2500_0.7500_0.0125_0.0000_151_5.0000_20.sav
galpy/df/data/dfcorrection_dehnendf_expSurfaceSigmaProfile_0.2500_0.7500_0.2000_0.0000_151_5.0000_20.sav
galpy/df/data/dfcorrection_dehnendf_expSurfaceSigmaProfile_0.3333_0.6667_0.0125_0.0000_151_5.0000_20.sav
galpy-1.11.1.dist-info/licenses/AUTHORS.txt
galpy-1.11.1.dist-info/licenses/LICENSE
galpy-1.11.1.dist-info/METADATA
galpy-1.11.1.dist-info/WHEEL
galpy-1.11.1.dist-info/top_level.txt
galpy-1.11.1.dist-info/RECORD
