Metadata-Version: 2.4
Name: galpy
Version: 1.11.1
Summary: Galactic Dynamics in python
Home-page: http://github.com/jobovy/galpy
Author: Jo Bovy
Author-email: bovy@astro.utoronto.ca
License: New BSD
Classifier: Development Status :: 6 - Mature
Classifier: Intended Audience :: Science/Research
Classifier: License :: OSI Approved :: BSD License
Classifier: Operating System :: OS Independent
Classifier: Programming Language :: C
Classifier: Programming Language :: Python :: 3.9
Classifier: Programming Language :: Python :: 3.10
Classifier: Programming Language :: Python :: 3.11
Classifier: Programming Language :: Python :: 3.12
Classifier: Programming Language :: Python :: 3.13
Classifier: Programming Language :: Python :: 3.14
Classifier: Environment :: WebAssembly :: Emscripten
Classifier: Topic :: Scientific/Engineering :: Astronomy
Classifier: Topic :: Scientific/Engineering :: Physics
Requires-Python: >=3.9
License-File: LICENSE
License-File: AUTHORS.txt
Requires-Dist: packaging
Requires-Dist: numpy>=1.7
Requires-Dist: scipy
Requires-Dist: matplotlib
Provides-Extra: docs
Requires-Dist: sphinxext-opengraph; extra == "docs"
Requires-Dist: sphinx-design; extra == "docs"
Requires-Dist: markupsafe==2.0.1; extra == "docs"
Dynamic: author
Dynamic: author-email
Dynamic: classifier
Dynamic: description
Dynamic: description-content-type
Dynamic: home-page
Dynamic: license
Dynamic: license-file
Dynamic: provides-extra
Dynamic: requires-dist
Dynamic: requires-python
Dynamic: summary
